streamlit_login_page/__init__.py
streamlit_login_page/frontend/index.html
streamlit_login_page/frontend/main.js
streamlit_login_page/frontend/streamlit-component-lib.js
streamlit_login_page/frontend/style.css
streamlit_login_page-0.1.9.dist-info/LICENSE
streamlit_login_page-0.1.9.dist-info/METADATA
streamlit_login_page-0.1.9.dist-info/WHEEL
streamlit_login_page-0.1.9.dist-info/top_level.txt
streamlit_login_page-0.1.9.dist-info/RECORD
