Metadata-Version: 2.1
Name: streamlit-login-page
Version: 0.1.9
Summary: Streamlit component that allows you to do X
Author: Anthony Alteirac
Author-email: anthony@alteirac.com
Requires-Python: >=3.7
License-File: LICENSE
Requires-Dist: streamlit >=1.2
Requires-Dist: jinja2
